recent_earthquake/__init__.py
last_earthquake-0.1.0.dist-info/LICENSE
last_earthquake-0.1.0.dist-info/METADATA
last_earthquake-0.1.0.dist-info/WHEEL
last_earthquake-0.1.0.dist-info/top_level.txt
last_earthquake-0.1.0.dist-info/RECORD
