Metadata-Version: 2.1
Name: last-earthquake
Version: 0.1.0
Summary: This package will get the latest earthquake data from BMKG | Badan Meteorologi, Klimatologi, dan Geofisika
Home-page: https://github.com/ArN-1/Indonesian-earthquake-monitoring
Author: Nur Arif
Author-email: nurarif0151@gmail.com
Project-URL: Website, https://nurarif.com
Classifier: Programming Language :: Python :: 3
Classifier: License :: OSI Approved :: GNU General Public License v3 (GPLv3)
Classifier: Operating System :: OS Independent
Requires-Python: >=3.8
License-File: LICENSE
